{
    "homepage": "https://pdf.abbyy.com/",
    "description": "ABBYY FineReader 是一款一体化的OCR 和PDF 软件应用程序，集优秀的文档转换、PDF 管理和文档比较于一身。",
    "version": "16.0.14.7295",
    "url": "http://soft.102323.xyz:9090/ABBYY-FineReader-PDF-v16.0.14.7295-Portable.7z/#dl.7z",
    "hash": "9318F2326FFBBEEF7ACC91BDB459D46ABFC5052DA106DAA12ACB39A65416D1F6",
    "bin": "FineReader16Portable.exe",
    "shortcuts": [
        [
            "FineReader16Portable.exe",
            "ABBYY FineReader PDF 16"
        ]
    ]
}
