{
    "version": "0.1.2",
    "architecture": {
        "64bit": {
            "url": "https://github.com/apono-io/apono-cli/releases/download/v0.1.2/apono-cli_0.1.2_windows_amd64.zip",
            "bin": [
                "apono.exe"
            ],
            "hash": "00e790adff6443187a16c7cd2273b9f6a7b36e3e1072c0d99530d648fff5ec40"
        }
    },
    "homepage": "https://www.apono.io",
    "license": "Apache-2.0",
    "description": "View, request and receive permissions to services, DBs and applications."
}
