{
    "version": "2023.8.2",
    "description": "A GUI inspector for mobile apps and more, powered by a (separately installed) Appium server",
    "homepage": "https://github.com/appium/appium-inspector",
    "license": "Apache v2",
    "url": "https://github.com/appium/appium-inspector/releases/download/v2023.8.2/Appium-Inspector-windows-2023.8.2.zip",
    "hash": "38dcbb8e381832fc6c9fffd73f51996ec719cd2c7259d97cc176c5513e6f3497",
    "checkver": "github",
    "shortcuts": [
        [
            "Appium Inspector.exe",
            "Appium Inspector"
        ]
    ],
    "autoupdate": {
        "url": "https://github.com/appium/appium-inspector/releases/download/v$version/Appium-Inspector-windows-$version.zip"
    }
}
