{
    "homepage": "https://www.bitvise.com/ssh-client",
    "license": {
        "identifier": "Freeware",
        "url": "https://www.bitvise.com/ssh-client-license"
    },
    "version": "9.31",
    "url": "https://dl.bitvise.com/BvSshClient-Inst.exe",
    "hash": "38d5c2b7141e596d2a2a4d35163982821f786b50ce05238efb20a2ddf186aee6",
    "installer": {
        "script": [
            "Invoke-ExternalCommand \"$dir\\BvSshClient-Inst.exe\" -ArgumentList @('-acceptEULA') -RunAs | Out-Null",
            "Remove-Item \"$dir\\BvSshClient-Inst.exe\""
        ]
    },
    "uninstaller": {
        "script": [
            "$pg_x86 = (Get-Item Env:programfiles`(x86`)).Value",
            "Invoke-ExternalCommand \"$pg_x86\\Bitvise SSH Client\\uninst.exe\" -ArgumentList @('-unat', '\"Bitvise SSH Client\"') -RunAs | Out-Null"
        ]
    },
    "checkver": {
        "url": "https://www.bitvise.com/ssh-client-download",
        "regex": "Current version: ([\\d.]+)"
    },
    "autoupdate": {
        "url": "https://dl.bitvise.com/BvSshClient-Inst.exe"
    }
}
