{
    "version": "8391",
    "description": "Chromium's certificate revocation list",
    "homepage": "https://www.chromium.org/Home/chromium-security/crlsets/",
    "license": "BSD-3-Clause",
    "url": "https://www.google.com/dl/release2/chrome_component/acnmzy2nrgglqswmde6nm37krurq_8391/hfnkpimlhhgieaddgfemjhofmfblmnib_8391_all_cch5w7vscsxikb3z6wwnze3bpi.crx3",
    "hash": "d3a9eb7e1e40a920e2784a26dd7bd99e05177612946ff62649a2241362bc5511",
    "installer": {
        "script": [
            "$dest = \"$dir\\CertificateRevocation\"",
            "Expand-7zipArchive \"$dir\\$fname\" $dest -Removal",
            "Set-Content \"$dest\\manifest.fingerprint\" \"1.$($manifest.hash)\" -NoNewline"
        ]
    },
    "checkver": {
        "script": [
            "$url = 'https://clients2.google.com/service/update2/crx?x=id%3Dhfnkpimlhhgieaddgfemjhofmfblmnib%26v%3D%26uc%26acceptformat%3Dcrx3'",
            "$cont = Invoke-RestMethod -UseBasicParsing -Method Get -Headers @{'Accept-Encoding'='gzip'} -MaximumRedirection 0 -Uri $url",
            "$cont = $cont.gupdate.app.updatecheck",
            "Write-Output ('version:\"' + $cont.version + '\"') ('url:\"' + $cont.codebase + '\"')"
        ],
        "regex": "version:\"(\\d+)\"\\surl:\"(?:https?://.+/(?<urlone>.+)/(?<basename>.+)\\.crx3)\""
    },
    "autoupdate": {
        "url": "https://www.google.com/dl/release2/chrome_component/$matchUrlone/$matchBasename.crx3",
        "hash": {
            "url": "https://clients2.google.com/service/update2/crx?x=id%3Dhfnkpimlhhgieaddgfemjhofmfblmnib%26v%3D%26uc%26acceptformat%3Dcrx3",
            "regex": "hash_sha256=\"([a-fA-F0-9]{64})\""
        }
    }
}
