{
    "version": "0.9.2",
    "architecture": {
        "32bit": {
            "url": "https://github.com/mcornick/clilol/releases/download/v0.9.2/clilol_0.9.2_windows_386.zip",
            "bin": [
                "clilol.exe"
            ],
            "hash": "3f06a1b5b16d70fe686edfad445946102b446f79752208a05af43dc49c4097aa"
        },
        "64bit": {
            "url": "https://github.com/mcornick/clilol/releases/download/v0.9.2/clilol_0.9.2_windows_amd64.zip",
            "bin": [
                "clilol.exe"
            ],
            "hash": "05c99cbd5344861d7cb25a0ea2a3653ea87f64f6021318afd022898c79aee2a5"
        }
    },
    "homepage": "https://mcornick.com/clilol/",
    "license": "MPL-2.0",
    "description": "A CLI for omg.lol"
}
