{
    "version": "2.8.0",
    "description": "Set of tools to store relational databases in a standard archival format",
    "homepage": "https://database-preservation.com/",
    "license": "GPL-3.0-only",
    "url": "https://github.com/keeps/dbptk-desktop/releases/download/v2.8.0/dbptk-desktop-2.8.0.exe#/dl.7z",
    "hash": "sha512:5270087f50f7f3ca5aca0e528af95f83897ede2cf7cde6f3ee1c90e5b94901a8569dbff1a25543640bf59f295735cf2e3587b5f4476a3b140d431ec36ebd7146",
    "architecture": {
        "64bit": {
            "pre_install": "Expand-7zipArchive \"$dir\\`$PLUGINSDIR\\app-64.7z\" \"$dir\""
        },
        "32bit": {
            "pre_install": "Expand-7zipArchive \"$dir\\`$PLUGINSDIR\\app-32.7z\" \"$dir\""
        }
    },
    "post_install": "Remove-Item \"$dir\\`$*\", \"$dir\\Uninstall*\" -Recurse",
    "bin": "dbptk-desktop.exe",
    "shortcuts": [
        [
            "dbptk-desktop.exe",
            "DBPTK Desktop"
        ]
    ],
    "checkver": {
        "github": "https://github.com/keeps/dbptk-desktop"
    },
    "autoupdate": {
        "url": "https://github.com/keeps/dbptk-desktop/releases/download/v$version/dbptk-desktop-$version.exe#/dl.7z",
        "hash": {
            "url": "$baseurl/latest.yml",
            "regex": "sha512:\\s+$base64"
        }
    }
}
