{
    "version": "18.0",
    "description": "DDraceNetwork, a free cooperative platformer game",
    "homepage": "https://ddnet.org/",
    "license": "SIL Open Font License",
    "architecture": {
        "64bit": {
            "url": "https://ddnet.org/downloads/DDNet-18.0-win64.zip",
            "hash": "5c173de01536950ba09b0859da406277675530788fa6ba1f3bf698005b948d2e",
            "extract_dir": "DDNet-18.0-win64"
        },
        "32bit": {
            "url": "https://ddnet.org/downloads/DDNet-18.0-win32.zip",
            "hash": "ab8dae97e1e21698dd1b4165d29e07e213c1a15fd172b85118cd2c1a14de35c3",
            "extract_dir": "DDNet-18.0-win32"
        }
    },
    "checkver": {
        "url": "https://ddnet.org/downloads/",
        "regex": "DDNet-([\\d.]+)-win64.zip"
    },
    "autoupdate": {
        "architecture": {
            "64bit": {
                "url": "https://ddnet.org/downloads/DDNet-$version-win64.zip",
                "extract_dir": "DDNet-$version-win64"
            },
            "32bit": {
                "url": "https://ddnet.org/downloads/DDNet-$version-win32.zip",
                "extract_dir": "DDNet-$version-win32"
            }
        },
        "hash": {
            "url": "https://ddnet.org/downloads/DDNet-$version.sha256",
            "regex": ""
        }
    },
    "shortcuts": [
        [
            "DDNet.exe",
            "DDNet"
        ]
    ]
}
