{
    "version": "0.12.0",
    "description": "Torrent client with on-demand file downloading as a filesystem.",
    "homepage": "https://distribyted.com",
    "license": "GPL-3.0-or-later",
    "architecture": {
        "64bit": {
            "url": "https://github.com/distribyted/distribyted/releases/download/v0.12.0/distribyted-v0.12.0-windows-amd64.exe#/distribyted.exe",
            "hash": "7c964f9dcaa936c7e284c81667e5b214741594852bf36fa84faf9e36e59bad3f"
        }
    },
    "bin": "distribyted.exe",
    "shortcuts": [
        [
            "distribyted.exe",
            "Distribyted"
        ]
    ],
    "persist": "distribyted-data",
    "checkver": {
        "github": "https://github.com/distribyted/distribyted"
    },
    "autoupdate": {
        "architecture": {
            "64bit": {
                "url": "https://github.com/distribyted/distribyted/releases/download/v$version/distribyted-v$version-windows-amd64.exe#/distribyted.exe"
            }
        }
    }
}
