{
    "version": "8.0.100",
    "description": ".NET is a free, cross-platform, open source developer platform for building many different types of applications.",
    "homepage": "https://www.microsoft.com/net/",
    "license": "MIT",
    "suggest": {
        "vcredist": "extras/vcredist2022"
    },
    "architecture": {
        "64bit": {
            "url": "https://dotnetcli.azureedge.net/dotnet/Sdk/8.0.100/dotnet-sdk-8.0.100-win-x64.zip",
            "hash": "sha512:69ee73c56c78c94c186c0fd1b06ce1a7325979f7680857dc1a05d516feb9f0ffe990c2c0441caed1de98a0d0ae3923cc3e04525f91d96306d611e481a24f9fb4"
        }
    },
    "env_add_path": ".",
    "env_set": {
        "DOTNET_ROOT": "$dir",
        "MSBuildSDKsPath": "$dir\\sdk\\$version\\Sdks"
    },
    "pre_uninstall": "info 'If the uninstall fails with a message saying that access is denied, you may need to log out of your current account, log back in and try again.'",
    "checkver": {
        "url": "https://dotnetcli.blob.core.windows.net/dotnet/release-metadata/releases-index.json",
        "jsonpath": "$..releases-index[?(@.release-type == 'lts' && @.support-phase == 'active')].latest-sdk",
        "regex": "([\\d.]+)"
    },
    "autoupdate": {
        "architecture": {
            "64bit": {
                "url": "https://dotnetcli.azureedge.net/dotnet/Sdk/$version/dotnet-sdk-$version-win-x64.zip"
            }
        },
        "hash": {
            "url": "https://dotnetcli.blob.core.windows.net/dotnet/release-metadata/$majorVersion.$minorVersion/releases.json",
            "regex": "(?s)$basename.*?$sha512"
        }
    }
}
