{
    "version": "1.2.0.r10982",
    "description": "Two pane file manager inspired by Total Commander",
    "homepage": "https://doublecmd.sourceforge.io/",
    "license": "GPL-2.0-only",
    "architecture": {
        "64bit": {
            "url": "https://doublecmd.sourceforge.io/snapshots/doublecmd-1.2.0.r10982.x86_64-win64.7z",
            "hash": "3d0b17145772047431e888464d3d5404174e058165f73a72c3ab165de250dca6"
        },
        "32bit": {
            "url": "https://doublecmd.sourceforge.io/snapshots/doublecmd-1.2.0.r10982.i386-win32.7z",
            "hash": "bfab9c17405fc1a73f6fd8bbdac24f822f1a2a38ee3233c41a00bc616fc23695"
        }
    },
    "bin": "doublecmd.exe",
    "shortcuts": [
        [
            "doublecmd.exe",
            "Double Commander"
        ]
    ],
    "checkver": {
        "url": "https://doublecmd.sourceforge.io/site/eng/snapshots.php",
        "regex": "doublecmd-([\\d.r]+)\\.i386-win32\\.7z"
    },
    "autoupdate": {
        "architecture": {
            "64bit": {
                "url": "https://doublecmd.sourceforge.io/snapshots/doublecmd-$version.x86_64-win64.7z"
            },
            "32bit": {
                "url": "https://doublecmd.sourceforge.io/snapshots/doublecmd-$version.i386-win32.7z"
            }
        }
    }
}
