{
    "version": "1.1.0.r10621",
    "description": "Two pane file manager inspired by Total Commander",
    "homepage": "https://doublecmd.sourceforge.io/",
    "license": "GPL-2.0-only",
    "architecture": {
        "64bit": {
            "url": "https://doublecmd.sourceforge.io/snapshots/doublecmd-1.1.0.r10621.x86_64-win64.7z",
            "hash": "1f7b14c5a0a49fc73ebb0479621d5e05373cb15cfb8cebe02e9c564586ab4a23"
        },
        "32bit": {
            "url": "https://doublecmd.sourceforge.io/snapshots/doublecmd-1.1.0.r10621.i386-win32.7z",
            "hash": "e2256171d0f4cc495139d299d81eaa4ae1812df00a5174849efa9b83dcaa6285"
        }
    },
    "bin": "doublecmd.exe",
    "shortcuts": [
        [
            "doublecmd.exe",
            "Double Commander"
        ]
    ],
    "checkver": {
        "url": "https://doublecmd.sourceforge.io/site/eng/snapshots.php",
        "regex": "doublecmd-([\\d.r]+)\\.i386-win32\\.7z"
    },
    "autoupdate": {
        "architecture": {
            "64bit": {
                "url": "https://doublecmd.sourceforge.io/snapshots/doublecmd-$version.x86_64-win64.7z"
            },
            "32bit": {
                "url": "https://doublecmd.sourceforge.io/snapshots/doublecmd-$version.i386-win32.7z"
            }
        }
    }
}
