{
    "version": "1.14.1",
    "description": "使用图形化的 Scrcpy 显示和控制您的 Android 设备",
    "homepage": "https://github.com/viarotel-org/escrcpy",
    "license": "MIT",
    "architecture": {
        "64bit": {
            "url": "https://github.com/viarotel-org/escrcpy/releases/download/v1.14.1/Escrcpy-1.14.1-win-x64.zip",
            "hash": "1e2f40dabde1bf8c1617209aa1c1320ebdc886b9242e97523884de4a67ba5110"
        },
        "arm64": {
            "url": "https://github.com/viarotel-org/escrcpy/releases/download/v1.14.1/Escrcpy-1.14.1-win-arm64.zip",
            "hash": "a1bb50fb4f096f571a0cbde6420e962ba3bde2d58c1e37f810a72476f81d8581"
        }
    },
    "shortcuts": [
        [
            "Escrcpy.exe",
            "Escrcpy",
            "--user-data-dir=\"$dir\\User Data\""
        ]
    ],
    "persist": "User Data",
    "checkver": "github",
    "autoupdate": {
        "architecture": {
            "64bit": {
                "url": "https://github.com/viarotel-org/escrcpy/releases/download/v$version/Escrcpy-$version-win-x64.zip"
            },
            "arm64": {
                "url": "https://github.com/viarotel-org/escrcpy/releases/download/v$version/Escrcpy-$version-win-arm64.zip"
            }
        }
    }
}
