{
    "version": "4.5.0.4480",
    "description": "身躯小巧，性能卓越，自定义功能完善，丰富的主题和脚本，完美的编码、大字符集字符显示，无论您是哪个级别的码农，EverEdit都会给您带来不一样的体验！",
    "homepage": "https://www.everedit.net/",
    "license": "Others",
    "url": "http://116.198.40.241/everedit_win64_4480_portable.zip",
    "hash": "b9b5aa353542be83b7c4e0b249c95dfa8497ad985d4957390b2425c9c95000f9",
    "shortcuts": [
        [
            "EverEdit.exe",
            "EverEdit"
        ]
    ],
    "persist": [
        "update",
        "macro",
        "plugin",
        "theme",
        "syntax",
        "update.log",
        "history.ini",
        "session.ini",
        "setting.ini",
        "cache.data",
        "key.ini",
        "mylist.txt"
    ],
    "autoupdate": {
        "url": "http://116.198.40.241/everedit_win64_$buildVersion_portable.zip"
    }
}
