{
    "homepage": "https://www.ponsoftware.com/",
    "version": "8.97",
    "license": "https://www.ponsoftware.com/archiver/regist.htm",
    "architecture": {
        "64bit": {
            "url": "https://www.ponsoftware.com/archiver/explzh/explz897_x64.exe#/dl.7z",
            "hash": "0282999bc96a0ff6a92d6584cf4dc80b6c12bdf0cec283017edf0a7da3167a82"
        },
        "32bit": {
            "url": "https://www.ponsoftware.com/archiver/explzh/explz897.exe#/dl.7z",
            "hash": "1fa428d560806ba72e74371ed79a6504f05b3220bdd1b44c4bcb97447d3eb228"
        }
    },
    "installer": {
        "script": [
            "",
            "InfDefaultInstall \"$dir\\x64\\EXPLZH.INF\"",
            ""
        ]
    },
    "bin": "Explzh.exe",
    "shortcuts": [
        [
            "Explzh.exe",
            "Explzh"
        ]
    ],
    "post_install": [
        "",
        "# Parrent path",
        "$regpath = 'HKCU:\\Software\\Pon\\'",
        "if (-not (Test-Path \"$regpath\")) { New-Item -Path \"$regpath\" | Out-Null }",
        "$regpath = 'HKCU:\\Software\\Pon\\Explzh\\'",
        "if (-not (Test-Path \"$regpath\")) { New-Item -Path \"$regpath\" | Out-Null }",
        "# ExplzhDir",
        "$regpath = 'HKCU:\\Software\\Pon\\Explzh\\Folders\\'",
        "if (-not (Test-Path \"$regpath\")) { New-Item -Path \"$regpath\" | Out-Null }",
        "$regname = 'ExplzhDir'",
        "$regvalue = Get-ItemProperty -Path \"$regpath\" -Name \"$regname\" -ErrorAction SilentlyContinue",
        "if ($regvalue -eq $null) {",
        "Set-ItemProperty \"$regpath\" -Name \"$regname\" -Value \"$dir\"",
        "}",
        ""
    ],
    "uninstaller": {
        "script": [
            "",
            "Copy-Item \"$dir\\associate.exe\" $Env:Temp",
            "Copy-Item \"$dir\\install.exe\" $Env:Temp",
            "&\"$Env:Temp\\install.exe\" \"/d\"",
            ""
        ]
    },
    "checkver": {
        "url": "https://www.ponsoftware.com/archiver/download.htm",
        "re": "Explzh Ver\\.([\\d.]+) \\("
    },
    "autoupdate": {
        "architecture": {
            "64bit": {
                "url": "https://www.ponsoftware.com/archiver/explzh/explz$cleanVersion_x64.exe#/dl.7z"
            },
            "32bit": {
                "url": "https://www.ponsoftware.com/archiver/explzh/explz$cleanVersion.exe#/dl.7z"
            }
        }
    }
}
