{
    "version": "1.2.0",
    "description": "Follow your RSS and Social Media Feeds",
    "homepage": "https://feeddeck.app",
    "license": "MIT",
    "architecture": {
        "64bit": {
            "url": "https://github.com/feeddeck/feeddeck/releases/download/v1.2.0/feeddeck-windows-x86_64.zip",
            "hash": "13a189edf19a9a102c95084eca616ee09f549b339279e7db9cf1d0f1b81c77c6",
            "pre_install": "Expand-7zipArchive \"$dir\\feeddeck.msix\" -Removal | Out-Null"
        }
    },
    "shortcuts": [
        [
            "feeddeck.exe",
            "FeedDeck"
        ]
    ],
    "checkver": {
        "github": "https://github.com/feeddeck/feeddeck"
    },
    "autoupdate": {
        "architecture": {
            "64bit": {
                "url": "https://github.com/feeddeck/feeddeck/releases/download/v$version/feeddeck-windows-x86_64.zip"
            }
        }
    }
}
