{
    "version": "109948",
    "description": "A complete, cross-platform solution to record, convert and stream audio and video.",
    "homepage": "https://ffmpeg.org",
    "license": "GPL-3.0-or-later",
    "architecture": {
        "64bit": {
            "url": "https://github.com/BtbN/FFmpeg-Builds/releases/download/autobuild-2023-03-01-14-07/ffmpeg-N-109948-ge026e29460-win64-gpl-shared.zip",
            "hash": "85d4fae4da0d64cee2c20bb37d3acfab3b572924a03a1ac27c2acad463b993c1",
            "extract_dir": "ffmpeg-N-109948-ge026e29460-win64-gpl-shared"
        }
    },
    "bin": [
        "bin\\ffmpeg.exe",
        "bin\\ffplay.exe",
        "bin\\ffprobe.exe"
    ],
    "checkver": {
        "url": "https://github.com/BtbN/FFmpeg-Builds/releases",
        "regex": "/autobuild-(?<time>[\\d-]+)/ffmpeg-N-(\\d+)-g(?<hash>[a-z\\d]+)-win64-gpl-shared\\.zip"
    },
    "autoupdate": {
        "architecture": {
            "64bit": {
                "url": "https://github.com/BtbN/FFmpeg-Builds/releases/download/autobuild-$matchTime/ffmpeg-N-$version-g$matchHash-win64-gpl-shared.zip",
                "extract_dir": "ffmpeg-N-$version-g$matchHash-win64-gpl-shared"
            }
        }
    }
}
