{
    "version": "0.0.2",
    "description": "Geld. A command line tool for tracking money and budgets.",
    "homepage": "https://github.com/mrusme/geld",
    "license": "GPL-3.0-or-later",
    "architecture": {
        "64bit": {
            "url": "https://github.com/mrusme/geld/releases/download/v0.0.2/geld_0.0.2_windows_amd64.tar.gz",
            "hash": "c9108713d9d07617792e79d666620fd56a542e60788192c7b1ebf69ed7a4efe2"
        },
        "32bit": {
            "url": "https://github.com/mrusme/geld/releases/download/v0.0.2/geld_0.0.2_windows_386.tar.gz",
            "hash": "95ac6230e6d45dd950ad067f38e33504dfd1ba83ce5a93bcd5824542a67b22e9"
        },
        "arm64": {
            "url": "https://github.com/mrusme/geld/releases/download/v0.0.2/geld_0.0.2_windows_arm64.tar.gz",
            "hash": "ff64d9694d771cc4c5e50dbb07bf8c3cd9b5e146911f4114b5f8d2e886244df0"
        }
    },
    "bin": "geld.exe",
    "checkver": "github",
    "autoupdate": {
        "architecture": {
            "64bit": {
                "url": "https://github.com/mrusme/geld/releases/download/v$version/geld_$version_windows_amd64.tar.gz"
            },
            "32bit": {
                "url": "https://github.com/mrusme/geld/releases/download/v$version/geld_$version_windows_386.tar.gz"
            },
            "arm64": {
                "url": "https://github.com/mrusme/geld/releases/download/v$version/geld_$version_windows_arm64.tar.gz"
            }
        },
        "hash": {
            "url": "$baseurl/geld_$version_checksums.txt"
        }
    }
}
