{
    "version": "3.0.3",
    "description": "Unlocks the 60 fps cap in Genshin Impact",
    "homepage": "https://github.com/34736384/genshin-fps-unlock",
    "license": "Freeware",
    "suggest": {
        ".NET Desktop Runtime": "extras/windowsdesktop-runtime"
    },
    "architecture": {
        "64bit": {
            "url": "https://github.com/34736384/genshin-fps-unlock/releases/download/v3.0.3/unlockfps_nc.exe",
            "hash": "08f16aa2f37dcd7fb4748c360a12f17e1fef33906be4cb8586874237af6f5fec"
        }
    },
    "pre_install": "if (!(Test-Path \"$persist_dir\\fps_config.json\")) { Add-Content \"$dir\\fps_config.json\" '{}' -Encoding utf8 }",
    "shortcuts": [
        [
            "unlockfps_nc.exe",
            "Genshin FPS Unlocker"
        ]
    ],
    "persist": "fps_config.json",
    "checkver": "github",
    "autoupdate": {
        "architecture": {
            "64bit": {
                "url": "https://github.com/34736384/genshin-fps-unlock/releases/download/v$version/unlockfps_nc.exe"
            }
        }
    }
}
