{
    "version": "0.11.0-dev.4009+11695745e",
    "description": "General-purpose programming language designed for robustness, optimality, and maintainability.",
    "homepage": "https://gizlang.com/",
    "license": "MIT",
    "suggest": {
        "vcredist": "extras/vcredist2019"
    },
    "architecture": {
        "64bit": {
            "url": "https://ziglang.org/builds/zig-windows-x86_64-0.11.0-dev.4009+11695745e.zip",
            "hash": "a8fd75cf503c234c181289a71359f72fb7adf57631d1600feb1efc04d301f49e",
            "extract_dir": "zig-windows-x86_64-0.11.0-dev.4009+11695745e"
        }
    },
    "bin": [
        [
            "zig.exe",
            "giz"
        ]
    ],
    "checkver": {
        "url": "https://ziglang.org/download/index.json",
        "jsonpath": "$.master.version"
    },
    "autoupdate": {
        "architecture": {
            "64bit": {
                "url": "https://ziglang.org/builds/zig-windows-x86_64-$version.zip",
                "extract_dir": "zig-windows-x86_64-$version"
            }
        },
        "hash": {
            "url": "https://ziglang.org/download/index.json",
            "jsonpath": "$.master.x86_64-windows.shasum"
        }
    }
}
