{
    "version": "1.9.11",
    "architecture": {
        "32bit": {
            "url": "https://github.com/ddddddO/gtree/releases/download/v1.9.11/gtree_Windows_i386.zip",
            "bin": [
                "gtree.exe"
            ],
            "hash": "2b0c21069fa1671b1da44e4103529a59c823f1eab1a775329d4f1224148c2d8e"
        },
        "64bit": {
            "url": "https://github.com/ddddddO/gtree/releases/download/v1.9.11/gtree_Windows_x86_64.zip",
            "bin": [
                "gtree.exe"
            ],
            "hash": "aa031599284889e461fae74f47adeef9f41be3d4a9135904e5fd90fb8d01b158"
        },
        "arm64": {
            "url": "https://github.com/ddddddO/gtree/releases/download/v1.9.11/gtree_Windows_arm64.zip",
            "bin": [
                "gtree.exe"
            ],
            "hash": "86b833b3832952c22456f63a6f47ad5f9d355b4879ac6cc178adb4a7e5b6396f"
        }
    },
    "homepage": "https://github.com/ddddddO/gtree",
    "license": "BSD-2-Clause",
    "description": "This CLI uses Markdown to generate directory trees and directories itself, and also verifies directories."
}
