{
    "version": "3.1.363",
    "architecture": {
        "64bit": {
            "url": "https://github.com/blacktop/ipsw/releases/download/v3.1.363/ipswd_3.1.363_windows_x86_64.tar.gz",
            "bin": [
                "ipswd_3.1.363_windows_x86_64/ipswd.exe"
            ],
            "hash": "5f8cfb35d5f4d2610b57037270b7c9c496451eb6db033e7dccdb13b5ccbf8329"
        }
    },
    "homepage": "https://blacktop.github.io/ipsw",
    "license": "MIT",
    "description": "ipsw - Daemon"
}
