{
    "version": "1.4.7.162-fa67f4fe",
    "description": "Dex to Java decompiler (unstable build)",
    "homepage": "https://github.com/skylot/jadx",
    "license": "Apache-2.0",
    "suggest": {
        "JRE": "java/openjdk"
    },
    "url": "https://nightly.link/skylot/jadx/workflows/build-artifacts/master/jadx-1.4.7.162-fa67f4fe.zip",
    "hash": "2808524f4b623ddab73357b3a59b616ce6102e67e966d8fa3dda7c1def53d5ea",
    "bin": [
        "bin\\jadx.bat",
        "bin\\jadx-gui.bat"
    ],
    "shortcuts": [
        [
            "bin\\jadx-gui.bat",
            "jadx-gui"
        ]
    ],
    "checkver": {
        "url": "https://nightly.link/skylot/jadx/workflows/build-artifacts/master",
        "regex": "/jadx-([.\\w-]+)\\.zip</a>"
    },
    "autoupdate": {
        "url": "https://nightly.link/skylot/jadx/workflows/build-artifacts/master/jadx-$version.zip"
    }
}
