{
    "version": "1.11-1317",
    "description": "KDiff3 is a file and folder diff and merge tool",
    "homepage": "https://apps.kde.org/kdiff3/",
    "license": "LGPL-2.0-only",
    "architecture": {
        "64bit": {
            "url": "https://binary-factory.kde.org/job/KDiff3_Stable_win64/lastSuccessfulBuild/artifact/kdiff3-1.11-1317-windows-cl-msvc2019-x86_64.7z",
            "hash": "17592e759660c99244fbf5d37bdc09aea58813e4edb5386345789da68d10e1e1"
        }
    },
    "bin": "bin\\kdiff3.exe",
    "shortcuts": [
        [
            "bin\\kdiff3.exe",
            "KDiff3"
        ]
    ],
    "checkver": {
        "url": "https://binary-factory.kde.org/job/KDiff3_Stable_win64/",
        "regex": "kdiff3-([\\d.-]+)-windows-cl-msvc2019-x86_64\\.7z"
    },
    "autoupdate": {
        "architecture": {
            "64bit": {
                "url": "https://binary-factory.kde.org/job/KDiff3_Stable_win64/lastSuccessfulBuild/artifact/kdiff3-$version-windows-cl-msvc2019-x86_64.7z",
                "hash": {
                    "url": "$url.sha256"
                }
            }
        }
    }
}
