{
    "version": "0.28.0",
    "description": "Komga metadata fetcher",
    "homepage": "https://github.com/Snd-R/komf",
    "license": "MIT",
    "suggest": {
        "JDK": [
            "java/oraclejdk",
            "java/openjdk"
        ]
    },
    "notes": "Default URL is http://localhost:8085",
    "url": "https://github.com/Snd-R/komf/releases/download/0.28.0/komf-0.28.0.jar#/komf.jar",
    "hash": "09bc1084f056d4f36ea2b31389755d95d88ebbb4a6ca0d043ec18b8c15d28f56",
    "bin": [
        [
            "komf.jar",
            "komf",
            "--config-dir=\"$dir\\config\""
        ]
    ],
    "persist": "config",
    "checkver": {
        "github": "https://github.com/Snd-R/komf"
    },
    "autoupdate": {
        "url": "https://github.com/Snd-R/komf/releases/download/$version/komf-$version.jar#/komf.jar"
    }
}
