{
    "version": "0.2.1",
    "architecture": {
        "64bit": {
            "url": "https://github.com/j178/leetgo/releases/download/v0.2.1/leetgo_Windows_x86_64.zip",
            "bin": [
                "leetgo.exe"
            ],
            "hash": "854b1740c245d8f0e89d480cd5b4127acaf655fe3b525b497e63898c6a940079"
        }
    },
    "homepage": "https://github.com/j178/leetgo",
    "license": "MIT",
    "description": "leetgo is a command line tool for leetcode.com. It can help you to login, submit, test, and view your submissions."
}
