{
    "version": "0.1.0",
    "architecture": {
        "64bit": {
            "url": "https://github.com/suzuki-shunsuke/lintnet/releases/download/v0.1.0/lintnet_windows_amd64.zip",
            "bin": [
                "lintnet.exe"
            ],
            "hash": "ba642827552d0d006170f1d191e1e4e56e2d4b88803bc37caa4201d71526215f"
        },
        "arm64": {
            "url": "https://github.com/suzuki-shunsuke/lintnet/releases/download/v0.1.0/lintnet_windows_arm64.zip",
            "bin": [
                "lintnet.exe"
            ],
            "hash": "88cb604574dd4d24cc8e8e8e13e6afcd1fa1ea940e83d7c51735f8e937a7172c"
        }
    },
    "license": "MIT",
    "description": "General Linter powered by Jsonnet.\n"
}
