{
    "version": "4.10.5",
    "description": "An Arknights game assissant",
    "homepage": "https://maa.plus/",
    "license": "AGPL-3.0-only",
    "url": "https://github.com/MaaAssistantArknights/MaaAssistantArknights/releases/download/v4.10.5/MaaBundle-v4.10.5.zip",
    "hash": "md5:5d3e1045c38a168a4b69580c2251e7ea",
    "bin": "MeoAsstGUI.exe",
    "shortcuts": [
        [
            "MeoAsstGUI.exe",
            "MaaAssistantArknights"
        ]
    ],
    "suggest": {
        "emulators": [
            "nonportable/bluestacks-np",
            "nonportable/bluestacks-hyperv-np"
        ],
        "adb": "adb"
    },
    "checkver": {
        "github": "https://github.com/MaaAssistantArknights/MaaAssistantArknights"
    },
    "autoupdate": {
        "url": "https://github.com/MaaAssistantArknights/MaaAssistantArknights/releases/download/v$version/MaaBundle-v$version.zip",
        "hash": {
            "mode": "json",
            "url": "https://github.com/MaaAssistantArknights/MaaAssistantArknights/releases/download/v$version/checksum.json",
            "jsonpath": "$[0].file_hash"
        }
    }
}
