{
    "version": "0.4.0",
    "description": "Output how to install our application with the scoop installer for README.md like this.",
    "homepage": "https://github.com/hymkor/make-howto-insta11",
    "license": "MIT License",
    "architecture": {
        "32bit": {
            "url": "https://github.com/hymkor/make-howto-insta11/releases/download/v0.4.0/make-howto-insta11-v0.4.0-windows-386.zip",
            "hash": "44f14e2b85fc94e21289e5eeaf24f1e0feca02cb3ccfa8af7b5c52118854ff28"
        },
        "64bit": {
            "url": "https://github.com/hymkor/make-howto-insta11/releases/download/v0.4.0/make-howto-insta11-v0.4.0-windows-amd64.zip",
            "hash": "0d59760611d4ef9d7922b39178e24307551c2526cd7a5ba726425eb4961a8a1e"
        }
    },
    "bin": "make-howto-insta11.exe",
    "checkver": "github",
    "autoupdate": {
        "architecture": {
            "32bit": {
                "url": "https://github.com/hymkor/make-howto-insta11/releases/download/v$version/make-howto-insta11-v$version-windows-386.zip"
            },
            "64bit": {
                "url": "https://github.com/hymkor/make-howto-insta11/releases/download/v$version/make-howto-insta11-v$version-windows-amd64.zip"
            }
        }
    }
}
