{
    "version": "1.6.9",
    "description": "Mindolph is an open source personal knowledge management software for all desktop platforms.",
    "homepage": "https://github.com/mindolph/Mindolph",
    "license": "GPL-3.0",
    "url": "https://github.com/mindolph/Mindolph/releases/download/v1.6.9/Mindolph-1.6.9.msi",
    "hash": "b10e4999cf7eeef58694cfbe9e6368d419af7a232cb4f36c2d3d59a1be6703a4",
    "extract_dir": "Mindolph",
    "shortcuts": [
        [
            "Mindolph.exe",
            "Mindolph"
        ]
    ],
    "checkver": "github",
    "autoupdate": {
        "url": "https://github.com/mindolph/Mindolph/releases/download/v$version/Mindolph-$version.msi"
    }
}
