{
    "version": "1.20230508064410",
    "architecture": {
        "64bit": {
            "url": "https://github.com/nais/cli/releases/download/1.20230508064410/nais-cli_1.20230508064410_windows_amd64.tar.gz",
            "bin": [
                "nais.exe"
            ],
            "hash": "43054168a022599d91845dc1ab0d5a4d41745b43d4a90eeb10c06ab62c77c22e"
        }
    },
    "homepage": "https://github.com/nais/cli",
    "license": "MIT",
    "description": "Command-line interface for NAIS"
}
