{
  "version": "2024-02-01-105426",
  "architecture": {
    "64bit": {
      "url": "https://github.com/nais/device/releases/download/2024-02-01-105426/naisdevice.exe",
      "hash": "d3df8d1fad8355d42e8b27150a0864445fc0b6c09e8bd5ac36632575420b1224",
      "installer": {
        "script": [
          "Write-Output \"Executing installer at $dir\\$fname\"",
          "Invoke-ExternalCommand \"$dir\\$fname\" -RunAs | Out-Null"
        ]
      },
      "post_uninstall": [
        "if ($cmd -eq \"uninstall\") { Invoke-ExternalCommand \"$env:ProgramW6432\\NAV\\naisdevice\\uninstaller.exe\" -RunAs | Out-Null }"
      ]
    }
  },
  "autoupdate": {
    "64bit": {
      "url": "https://github.com/nais/device/releases/download/$version/naisdevice.exe"
    },
    "hash": {
      "url": "$url.sha256"
    }
  },
  "homepage": "https://github.com/nais/device",
  "checkver": "github",
  "license": "MIT",
  "description": "naisdevice is a application suite that enables NAV developers to connect to internal resources in a secure and friendly manner."
}
