{
    "version": "1.20230508072811",
    "architecture": {
        "64bit": {
            "url": "https://github.com/nais/cli/releases/download/1.20230508072811/nais-cli_1.20230508072811_windows_amd64.tar.gz",
            "bin": [
                "nais.exe"
            ],
            "hash": "6d32969f7043f6722a9cb6433dbf1a4af781ca1858be64d72b695224d316d943"
        }
    },
    "homepage": "https://github.com/nais/cli",
    "license": "MIT",
    "description": "Command-line interface for NAIS"
}
