{
    "version": "16.3.3",
    "homepage": "https://www.navicat.com",
    "architecture": {
        "64bit": {
            "url": "http://download.navicat.com/download/navicat163_premium_en_x64.exe",
            "hash": "2bfa1499b84b8ace8314bc3d487d8840612f947e420440013f3a885331b27af5"
        },
        "32bit": {
            "url": "http://download.navicat.com/download/navicat163_premium_en_x86.exe",
            "hash": "fde4eb448f440ce09c57e2b1c94e01c5b3fa36d67b6b7a791d5d2777a3d3374c"
        }
    },
    "checkver": {
        "url": "https://www.navicat.com/en/products/navicat-premium-release-note",
        "re": "Navicat Premium \\(Windows\\) version ([\\d\\.]+)"
    },
    "autoupdate": {
        "architecture": {
            "64bit": {
                "url": "http://download.navicat.com/download/navicat$majorVersion$minorVersion_premium_en_x64.exe"
            },
            "32bit": {
                "url": "http://download.navicat.com/download/navicat$majorVersion$minorVersion_premium_en_x86.exe"
            }
        }
    },
    "innosetup": true,
    "shortcuts": [
        [
            "navicat.exe",
            "Navicat Premium"
        ]
    ]
}
