{
    "homepage": "https://github.com/Tatsu-syo/noMeiryoUI",
    "description": "Windows system font setting tool on Windows 8.1/10",
    "license": "GPL-3.0-only",
    "version": "3.3.0",
    "url": "https://github.com/Tatsu-syo/noMeiryoUI/releases/download/TAG-3.3.0/noMeiryoUI3.3.0.zip",
    "hash": "3337838d450ab2068fb9aaea09193a1528531550a84776cfb089b1bd2e183550",
    "shortcuts": [
        [
            "noMeiryoUI.exe",
            "noMeiryoUI"
        ]
    ],
    "checkver": {
        "url": "https://github.com/Tatsu-syo/noMeiryoUI/releases/latest",
        "regex": "TAG-(?<version>[\\d\\.]+)"
    },
    "autoupdate": {
        "url": "https://github.com/Tatsu-syo/noMeiryoUI/releases/download/TAG-$version/noMeiryoUI$version.zip"
    }
}
