{
    "homepage": "https://github.com/cnlh/nps",
    "version": "0.26.11",
    "license": "GPL-3.0-only",
    "architecture": {
        "64bit": {
            "url": "https://github.com/cesaryuan/nps/releases/download/v0.26.11/windows_amd64_client.tar.gz",
            "hash": "7af37d06d3e214e95f1745cc7b5c7537d76cd841c70133ecf7734ec4e23cc0a7"
        },
        "32bit": {
            "url": "https://github.com/cesaryuan/nps/releases/download/v0.26.11/windows_386_client.tar.gz",
            "hash": "3a77456b36c0cecf5c734223dce62c9e2df1c30a39360843a026f94272c3c8b9"
        }
    },
    "persist": "conf",
    "bin": "npc.exe",
    "checkver": {
        "github": "https://github.com/cesaryuan/nps"
    },
    "autoupdate": {
        "architecture": {
            "64bit": {
                "url": "https://github.com/cesaryuan/nps/releases/download/v$version/windows_amd64_client.tar.gz"
            },
            "32bit": {
                "url": "https://github.com/cesaryuan/nps/releases/download/v$version/windows_386_client.tar.gz"
            }
        }
    }
}
