{
    "version": "14.14.4",
    "description": "All the official themes for Oh-My-Posh",
    "homepage": "https://ohmyposh.dev",
    "license": "MIT",
    "notes": "Refer to 'https://ohmyposh.dev/docs/installation/prompt' for shell specific configurations.",
    "url": "https://github.com/JanDeDobbeleer/oh-my-posh/releases/download/v14.14.4/themes.zip",
    "hash": "cd2dce56bf1c7fce996de96d12acb8a4f8b29eceaf85021c5d83df8b77089504",
    "depends": "oh-my-posh",
    "env_set": {
        "POSH_THEMES_PATH": "$dir"
    },
    "checkver": {
        "github": "https://github.com/JanDeDobbeleer/oh-my-posh"
    },
    "autoupdate": {
        "url": "https://github.com/JanDeDobbeleer/oh-my-posh/releases/download/v$version/themes.zip"
    }
}
