{
    "version": "18.6.4",
    "description": "All the official themes for Oh-My-Posh",
    "homepage": "https://ohmyposh.dev",
    "license": "MIT",
    "notes": "Refer to 'https://ohmyposh.dev/docs/installation/prompt' for shell specific configurations.",
    "url": "https://github.com/JanDeDobbeleer/oh-my-posh/releases/download/v18.6.4/themes.zip",
    "hash": "6a469c8c918c1842da848dee61d5b46719c6f5f272d65da9c776845af60b73c0",
    "depends": "oh-my-posh",
    "env_set": {
        "POSH_THEMES_PATH": "$dir"
    },
    "checkver": {
        "github": "https://github.com/JanDeDobbeleer/oh-my-posh"
    },
    "autoupdate": {
        "url": "https://github.com/JanDeDobbeleer/oh-my-posh/releases/download/v$version/themes.zip",
        "hash": {
            "url": "$url.sha256"
        }
    }
}
