{
    "version": "10.21.0-58",
    "description": "Postman™ portable app made with Portapps. A complete toolchain for API developers.",
    "homepage": "https://github.com/portapps/postman-portable",
    "license": "MIT",
    "architecture": {
        "64bit": {
            "url": "https://github.com/portapps/postman-portable/releases/download/10.21.0-58/postman-portable-win64-10.21.0-58.7z",
            "hash": "7ef62b91ad358a53fb76825f8650ea6a084b3a966c3c1c9ccbaea33eeb86c785"
        }
    },
    "bin": [
        [
            "postman-portable.exe",
            "Postman"
        ]
    ],
    "shortcuts": [
        [
            "postman-portable.exe",
            "Postman"
        ]
    ],
    "persist": [
        "data",
        "log"
    ],
    "checkver": {
        "url": "https://github.com/portapps/postman-portable/releases/latest",
        "regex": "releases/tag/([\\d.-]+)"
    },
    "autoupdate": {
        "architecture": {
            "64bit": {
                "url": "https://github.com/portapps/postman-portable/releases/download/$version/postman-portable-win64-$version.7z",
                "hash": {
                    "url": "$baseurl/checksums.txt",
                    "regex": "$sha256\\s+$basename"
                }
            }
        }
    }
}
