{
    "version": "1.4.480",
    "description": "pre-release version for quarto",
    "homepage": "https://quarto.org/",
    "license": "GPL-2.0-only",
    "architecture": {
        "64bit":{
            "url": "https://github.com/quarto-dev/quarto-cli/releases/download/v1.4.480/quarto-1.4.480-win.zip",
            "hash": "2356a47dd2c7cbb291070af06d60213f2e8323d9568f35f275d0912e14fbf49f"
        }
    },
    "bin": "bin\\quarto.exe",
    "checkver": {
        "url": "https://api.github.com/repositories/298579934/releases",
        "regex": "download/v([\\d.]+)/"
    },
    "autoupdate": {
        "architecture": {
            "64bit":{
                "url": "https://github.com/quarto-dev/quarto-cli/releases/download/v$version/quarto-$version-win.zip",
            }
        },
    }
}
