{
    "version": "1.4.504",
    "description": "pre-release version for quarto",
    "homepage": "https://quarto.org/",
    "license": "GPL-2.0-only",
    "architecture": {
        "64bit": {
            "url": "https://github.com/quarto-dev/quarto-cli/releases/download/v1.4.504/quarto-1.4.504-win.zip",
            "hash": "c9badb9f2f1eaf000c2b862b0c0d0d1b73c5db8ed17daa18228c1aabdd322bfc"
        }
    },
    "bin": "bin\\quarto.exe",
    "checkver": {
        "url": "https://api.github.com/repositories/298579934/releases",
        "regex": "download/v([\\d.]+)/"
    },
    "autoupdate": {
        "architecture": {
            "64bit": {
                "url": "https://github.com/quarto-dev/quarto-cli/releases/download/v$version/quarto-$version-win.zip"
            }
        }
    }
}
