{
    "version": "0.0.1",
    "architecture": {
        "32bit": {
            "url": "https://github.com/abhimanyu003/probe/releases/download/v0.0.1/probe_0.0.1_windows_386.tar.gz",
            "bin": [
                "probe.exe"
            ],
            "hash": "025e9d4ad95d47af02651d4f9b707e634e6385cc2bfb41794779e57fd4d5392e"
        },
        "64bit": {
            "url": "https://github.com/abhimanyu003/probe/releases/download/v0.0.1/probe_0.0.1_windows_amd64.tar.gz",
            "bin": [
                "probe.exe"
            ],
            "hash": "7870f87dac116eab65dbc25f6bcff111ddf843ba98c47556a76970fb2c7498b4"
        }
    },
    "homepage": "https://github.com/abhimanyu003/sttr",
    "license": "MIT",
    "description": "YAML + JQ end-to-end API testing tool."
}
