{
    "homepage": "https://github.com/be5invis/Sarasa-Gothic",
    "version": "0.40.1",
    "description": "This is SARASA GOTHIC, a CJK programming font based on Iosevka and Source Han Sans.",
    "license": "OFL-1.1",
    "url": "https://github.com/be5invis/Sarasa-Gothic/releases/download/v0.40.1/sarasa-gothic-ttc-0.40.1.7z",
    "hash": "7298053a19854b2240db2846082b9df631772c46e88912b27dbdcd3e247325d4",
    "checkver": "github",
    "autoupdate": {
        "url": "https://github.com/be5invis/Sarasa-Gothic/releases/download/v$version/sarasa-gothic-ttc-$version.7z"
    }
}
