{
    "version": "0.26.0",
    "description": "A blazing-fast modern Lua linter, with Roblox-tailored lints.",
    "homepage": "https://kampfkarren.github.io/selene/",
    "license": "MPL-2.0",
    "architecture": {
        "64bit": {
            "url": "https://github.com/Kampfkarren/selene/releases/download/0.26.0/selene-0.26.0-windows.zip",
            "hash": "81fa888b0267582afa934a59c99271ebe7f9274f35bed9646417eb618d69f41f"
        }
    },
    "bin": "selene.exe",
    "checkver": {
        "url": "https://github.com/Kampfkarren/selene/releases/latest",
        "regex": "tag/([\\d.]+)"
    },
    "autoupdate": {
        "architecture": {
            "64bit": {
                "url": "https://github.com/Kampfkarren/selene/releases/download/$version/selene-$version-windows.zip"
            }
        }
    }
}
