{
    "version": "202403150014",
    "description": "GeoIP data for sing-box (unofficial)",
    "homepage": "https://github.com/soffchen/sing-geoip",
    "license": "",
    "url": "https://github.com/soffchen/sing-geoip/releases/download/202403150014/geoip.db",
    "hash": "c353ff45929a752d19a82ff22e39dcd08661ec850b89e8f9e19fd9b0f53fbcdc",
    "checkver": "github",
    "autoupdate": {
        "url": "https://github.com/soffchen/sing-geoip/releases/download/$version/geoip.db",
        "hash": {
            "url": "$url.sha256sum"
        }
    }
}
