{
    "version": "0.0.73",
    "architecture": {
        "32bit": {
            "url": "https://github.com/sst/ion/releases/download/v0.0.73/sst-windows-i386.zip",
            "bin": [
                "sst.exe"
            ],
            "hash": "460a1bcfe8a33afc5f5115b16e58b15098ca1d05128fe720691f3e1320ebf878"
        },
        "64bit": {
            "url": "https://github.com/sst/ion/releases/download/v0.0.73/sst-windows-x86_64.zip",
            "bin": [
                "sst.exe"
            ],
            "hash": "79c106b91250eb4bb8b96ffc64333a2b89b6a7146783c441d6c27640313e1e4c"
        },
        "arm64": {
            "url": "https://github.com/sst/ion/releases/download/v0.0.73/sst-windows-arm64.zip",
            "bin": [
                "sst.exe"
            ],
            "hash": "ba15940341eed2df51b0836e7c344749066eca143dbdc6cd50eaa081d26dcf81"
        }
    },
    "homepage": "https://github.com/sst/ion",
    "license": "Apache 2.0",
    "description": "sst cli"
}
