{
    "version": "15324",
    "description": "Free PDF, eBook reader.",
    "homepage": "https://www.sumatrapdfreader.org",
    "license": "GPL-3.0-only,BSD-2-Clause",
    "architecture": {
        "64bit": {
            "url": "https://www.sumatrapdfreader.org/dl/prerel/15324/SumatraPDF-prerel-64.exe",
            "hash": "da6ee4a1b05af6901f77f0780d52130cc2d359eab1b4f34d02ad1ccb36cc8005"
        }
    },
    "pre_install": [
        "Get-Item \"$dir\\SumatraPDF*.exe\" | Rename-Item -NewName 'SumatraPDF.exe'",
        "$file = 'SumatraPDF-settings.txt'",
        "if (-not (Test-Path \"$persist_dir\\$file\")) {",
        "    Write-Host 'File' $file 'does not exists. Creating.' -f Yellow",
        "    $CONT = @('CheckForUpdates = false')",
        "    Set-Content \"$dir\\$file\" ($CONT -join \"`r`n\") -Encoding Ascii",
        "}"
    ],
    "bin": "SumatraPDF.exe",
    "shortcuts": [
        [
            "SumatraPDF.exe",
            "SumatraPDF"
        ]
    ],
    "persist": [
        "SumatraPDF-settings.txt",
        "sumatrapdfcache"
    ],
    "checkver": {
        "url": "https://kjkpubsf.sfo2.digitaloceanspaces.com/software/sumatrapdf/sumatralatest.js",
        "regex": "var sumLatestVer = (?<version>[\\d\\.]+);"
    },
    "autoupdate": {
        "architecture": {
            "64bit": {
                "url": "https://www.sumatrapdfreader.org/dl/prerel/$version/SumatraPDF-prerel-64.exe"
            }
        }
    }
}
