{
    "version": "0.9.15",
    "architecture": {
        "32bit": {
            "url": "https://github.com/pomdtr/sunbeam/releases/download/v0.9.15/sunbeam_Windows_i386.tar.gz",
            "bin": [
                "sunbeam.exe"
            ],
            "hash": "a6068eb626563be337ae7300f794cd995adbcbdd8ff54e369566b1a608a96bc1"
        },
        "64bit": {
            "url": "https://github.com/pomdtr/sunbeam/releases/download/v0.9.15/sunbeam_Windows_x86_64.tar.gz",
            "bin": [
                "sunbeam.exe"
            ],
            "hash": "3b06063755e58fd7a6c22359a084e40de23a4012dd566c064cbf557b4c44446d"
        }
    },
    "homepage": "https://pomdtr.github.io/sunbeam",
    "license": "MIT",
    "description": "Generate powerful UIs from simple scripts written in any language."
}
