{
    "version": "1.127.2",
    "architecture": {
        "64bit": {
            "url": "https://github.com/supabase/cli/releases/download/v1.127.2/supabase_windows_amd64.tar.gz",
            "bin": [
                "supabase.exe"
            ],
            "hash": "788669eec525300244d5e21ff2787c33affdef5eb1a8c1b729a4d726c8f9f8be"
        },
        "arm64": {
            "url": "https://github.com/supabase/cli/releases/download/v1.127.2/supabase_windows_arm64.tar.gz",
            "bin": [
                "supabase.exe"
            ],
            "hash": "28c6c7a06fb400a0a30d0a69fcd1cb9cd50a8ad2279842e4bf6b8f990f1d9c37"
        }
    },
    "homepage": "https://supabase.com",
    "license": "MIT",
    "description": "Supabase CLI (Beta)"
}
