{
    "version": "1.6.4",
    "description": "A single player word finding game based on Boggle™",
    "homepage": "https://gottcode.org/tanglet/",
    "license": "GPL-3.0",
    "notes": "",
    "architecture": {
        "64bit": {
            "url": "https://gottcode.org/tanglet/download/?os=windowsportable#/Tanglet.zip",
            "hash": "cca8b5d5ed986befd20d0aa0cbf27938645c71a4545919ec2ef59b2e6b849ad2"
        }
    },
    "extract_to": "",
    "bin": "Tanglet.exe",
    "shortcuts": [
        [
            "Tanglet.exe",
            "Tanglet"
        ]
    ],
    "persist": "Data",
    "checkver": {
        "github": "https://github.com/gottcode/tanglet"
    },
    "autoupdate": {
        "architecture": {
            "64bit": {
                "url": "https://gottcode.org/tanglet/download/?os=windowsportable#/Tanglet.zip"
            }
        }
    }
}
