{
    "version": "0.12.149",
    "description": "Tree-sitter Language Bundle for Emacs",
    "homepage": "https://github.com/emacs-tree-sitter/tree-sitter-langs",
    "license": "MIT",
    "url": "https://github.com/emacs-tree-sitter/tree-sitter-langs/releases/download/0.12.149/tree-sitter-grammars.x86_64-pc-windows-msvc.v0.12.149.tar.gz",
    "hash": "2fb1c712e7a8a99b0ee2f9e37dd5157281a7ee8fda1fdf1241240ebb32dcc617",
    "post_install": "Get-ChildItem $dir\\*.dll | Rename-Item -NewName { 'libtree-sitter-' + $_.Name }",
    "checkver": "github",
    "autoupdate": {
        "url": "https://github.com/emacs-tree-sitter/tree-sitter-langs/releases/download/$version/tree-sitter-grammars.x86_64-pc-windows-msvc.v$version.tar.gz"
    }
}
