{
    "homepage": "https://github.com/errata-ai/vale",
    "version": "2.23.0",
    "description": "Vale is a command-line tool that brings code-like linting to prose.",
    "checkver": {
        "url": "https://github.com/errata-ai/vale/releases/latest",
        "re": "v([\\d.]+[\\d](-rc..)?)<"
    },
    "architecture": {
        "64bit": {
            "url": "https://github.com/errata-ai/vale/releases/download/v2.23.0/vale_2.23.0_Windows_64-bit.zip",
            "hash": "e912dc6d771ff9e2649de6a741019c41adc47997f733447df71b135e7701131b"
        },
        "32bit": {
            "url": "https://github.com/errata-ai/vale/releases/download/v2.23.0/vale_2.23.0_Windows_64-bit.zip",
            "hash": "e912dc6d771ff9e2649de6a741019c41adc47997f733447df71b135e7701131b"
        }
    },
    "autoupdate": {
        "url": "https://github.com/errata-ai/vale/releases/download/v$version/vale_$version_Windows_64-bit.zip"
    },
    "bin": "vale.exe"
}
