{
    "version": "0.4.3",
    "description": "Vesktop is a cross platform desktop app aiming to give you a snappier Discord experience with Vencord pre-installed",
    "homepage": "https://github.com/Vencord/Vesktop",
    "license": "GPL-3.0",
    "notes": [
        "This scoop package is unofficial and not maintained by official Vencord Developers",
        "Please, do not request support there for the scoop package"
    ],
    "architecture": {
        "64bit": {
            "url": "https://github.com/Vencord/Vesktop/releases/download/v0.4.3/Vesktop-0.4.3-win.zip",
            "hash": "a41b879c0e17fa7e392a6c7be74308912b7b4ba5abdb6499b85fa1809900c821"
        }
    },
    "shortcuts": [
        [
            "vesktop.exe",
            "Vesktop"
        ]
    ],
    "checkver": {
        "github": "https://github.com/Vencord/Vesktop"
    },
    "autoupdate": {
        "architecture": {
            "64bit": {
                "url": "https://github.com/Vencord/Vesktop/releases/download/v$version/Vesktop-$version-win.zip"
            }
        }
    }
}
