{
    "version": "5.2.1",
    "description": "look up records for one or more IPs/networks in one or more .mmdb databases",
    "homepage": "https://github.com/t1m0thyj/WinDynamicDesktop",
    "license": "Freeware",
    "architecture": {
        "64bit": {
            "url": "https://github.com/t1m0thyj/WinDynamicDesktop/releases/download/v5.2.1/WinDynamicDesktop_5.2.1_x64_Portable.exe",
            "hash": "28b82925ee781bc465e382c165303811583a39031aadd8e5f5ede37872f55250",
            "shortcuts": [
                [
                    "WinDynamicDesktop_5.2.1_x64_Portable.exe",
                    "WinDynamicDesktop"
                ]
            ]
        },
        "32bit": {
            "url": "https://github.com/t1m0thyj/WinDynamicDesktop/releases/download/v5.2.1/WinDynamicDesktop_5.2.1_x86_Portable.exe",
            "hash": "db11088ba9a17eaffe5753c27df34e94cde6b2ecb6e80a3a34ffb4fb38b64eb8",
            "shortcuts": [
                [
                    "WinDynamicDesktop_5.2.1_x86_Portable.exe",
                    "WinDynamicDesktop"
                ]
            ]
        }
    },
    "installer": {
        "script": "if (!(Test-Path \"$persist_dir\\settings.json\")) { Set-Content -LiteralPath \"$dir\\settings.json\" -Value \"{}\" -Force }"
    },
    "persist": [
        "scripts",
        "themes",
        "settings.json"
    ],
    "checkver": "github",
    "autoupdate": {
        "architecture": {
            "64bit": {
                "url": "https://github.com/t1m0thyj/WinDynamicDesktop/releases/download/v$version/WinDynamicDesktop_$version_x64_Portable.exe",
                "shortcuts": [
                    [
                        "WinDynamicDesktop_$version_x64_Portable.exe",
                        "WinDynamicDesktop"
                    ]
                ]
            },
            "32bit": {
                "url": "https://github.com/t1m0thyj/WinDynamicDesktop/releases/download/v$version/WinDynamicDesktop_$version_x86_Portable.exe",
                "shortcuts": [
                    [
                        "WinDynamicDesktop_$version_x86_Portable.exe",
                        "WinDynamicDesktop"
                    ]
                ]
            }
        }
    }
}
