{
    "version": "3.11.4.0",
    "description": "Free, open-source and portable Python distribution for Windows",
    "homepage": "https://winpython.github.io/",
    "license": "MIT",
    "architecture": {
        "64bit": {
            "url": "https://github.com/winpython/winpython/releases/download/6.4.20230625final/Winpython64-3.11.4.0.exe#/dl.7z",
            "hash": "193233967bd2b6a6cd705ac3b17dac9c4864ae8e56744a2b89caed91f2fb6f05",
            "extract_dir": "WPy64-31140\\python-3.11.4.amd64"
        }
    },
    "bin": [
        "python.exe",
        "pythonw.exe",
        [
            "python.exe",
            "python3"
        ]
    ],
    "env_add_path": "scripts",
    "persist": "settings",
    "checkver": {
        "github": "https://github.com/winpython/winpython",
        "regex": "/download/(?<gitv>[\\d.]+)final/Winpython64-(?<version>[\\d.]+)\\.exe",
        "reverse": true
    },
    "autoupdate": {
        "architecture": {
            "64bit": {
                "url": "https://github.com/winpython/winpython/releases/download/$matchGitvfinal/Winpython64-$matchVersion.exe#/dl.7z",
                "extract_dir": "WPy64-$cleanVersion\\python-$majorVersion.$minorVersion.$patchVersion.amd64"
            }
        },
        "hash": {
            "url": "https://winpython.github.io/md5_sha1.txt",
            "regex": "$sha256\\s+\\|\\s+$basename"
        }
    }
}
