{
    "homepage": "http://www.nirsoft.net/utils/wireless_network_watcher.html",
    "description": "Wireless Network Watcher scans your wireless network and displays the list of all devices that are connected to your network",
    "version": "2.40",
    "url": "http://www.nirsoft.net/utils/wnetwatcher.zip",
    "hash": "a852f3ecfb6bf7acd7fc152176bcae27ef0d9b9833bf38a995db0ae25494d47a",
    "shortcuts": [
        [
            "WNetWatcher.exe",
            "WNetWatcher"
        ]
    ],
    "checkver": "Watcher v([\\d.]+)",
    "autoupdate": {
        "url": "http://www.nirsoft.net/utils/wnetwatcher.zip"
    }
}
