{
    "version": "0.1.4",
    "description": "Alternative xBrowserSync API that is a single binary and supports SQLite3, PostgreSQL and MySQL",
    "homepage": "https://github.com/mrusme/xbsapi",
    "license": "GPL-3.0-or-later",
    "architecture": {
        "64bit": {
            "url": "https://github.com/mrusme/xbsapi/releases/download/v0.1.4/xbsapi_0.1.4_windows_amd64.tar.gz",
            "hash": "50c6c64f66c3339005b957c41716d49e74721a9af6194df9e0543375d5f50c3d"
        },
        "32bit": {
            "url": "https://github.com/mrusme/xbsapi/releases/download/v0.1.4/xbsapi_0.1.4_windows_386.tar.gz",
            "hash": "0965b5af01d947205b6715f3a53dcacc7ad8f1fe2233dad77ce8f7a29f0459c8"
        },
        "arm64": {
            "url": "https://github.com/mrusme/xbsapi/releases/download/v0.1.4/xbsapi_0.1.4_windows_arm64.tar.gz",
            "hash": "7df9e963bfafe76374d01deab3825f9d39e8f32de25c717a487ead3ee1ddf95b"
        }
    },
    "bin": "xbsapi.exe",
    "checkver": "github",
    "autoupdate": {
        "architecture": {
            "64bit": {
                "url": "https://github.com/mrusme/xbsapi/releases/download/v$version/xbsapi_$version_windows_amd64.tar.gz"
            },
            "32bit": {
                "url": "https://github.com/mrusme/xbsapi/releases/download/v$version/xbsapi_$version_windows_386.tar.gz"
            },
            "arm64": {
                "url": "https://github.com/mrusme/xbsapi/releases/download/v$version/xbsapi_$version_windows_arm64.tar.gz"
            }
        },
        "hash": {
            "url": "$baseurl/xbsapi_$version_checksums.txt"
        }
    }
}
